{
  "editor.fontFamily": "'FiraCode Nerd Font', 'monospace', monospace",
  "editor.fontLigatures": true,
  "editor.fontSize": 14,
  "terminal.integrated.fontFamily": "'FiraCode Nerd Font'",
  "workbench.colorTheme": "Tokyo Night (Nix)",
  "[javascript]": {
    "editor.defaultFormatter": "biomejs.biome"
  },
  "editor.formatOnSave": true,
  "workbench.editorAssociations": {
    "{git,gitlens,chat-editing-snapshot-text-model,copilot,git-graph,git-graph-3}:/**/*.qrc": "default",
    "*.qrc": "qt-core.qrcEditor"
  },
  "vsicons.dontShowNewVersionMessage": true,
  "redhat.telemetry.enabled": false,
  "explorer.confirmDelete": false
}
